{"Source_Product_Review_ID": "twitter#Jones#332", "Review_Source": "Twitter", "Product_Name": "Dell XPS 13 (2020)", "Product_Category": "Intel Notebooks", "Product_Price": null, "Review_Date": "2020-09-24T19:51:08", "Review_Headline": null, "Review_Text": "Usar o XPS 13 da @DellnoBrasil nas \u00faltimas duas semanas foi algo \u00fanico. Ele mudou toda a minha rotina no home offic\u2026 https://t.co/w0ph0k9DxZ", "User_ID": 3590074461, "User_Name": "Jones", "User_Age": null, "User_Location": "Raccoon City", "Positive_Words": null, "Negetive_Words": null, "Review_Sentiment": null, "Review_Rating": null}
