{"Review_Headline":null,"Review_Date":"Fri Sep 11 16:57:26 +0000 2020","Review_Rating":null,"Product_Category":null,"Review_Source":"Twitter","Source_Product_Review_ID":"twitter#Geno#377","User_Location":"New Jersey, USA","Review_Text":"825GB will shrink to a bit over 600GB That sucks in truth. BUT XSX 1TB will turn to 825GB. So still regardless Both… https://t.co/m4AOw0JgEX","Review_Sentiment":null,"Positive_Words":null,"Product_Price":null,"User_Age":null,"Negetive_Words":null,"User_ID":430980275,"User_Name":"Geno","Product_Name":null}
