{"Review_Headline":null,"Review_Date":"Fri Sep 11 16:59:32 +0000 2020","Review_Rating":null,"Product_Category":null,"Review_Source":"Twitter","Source_Product_Review_ID":"twitter#YT:Breusley 🇭🇹#284","User_Location":null,"Review_Text":"So I’m selling my ps4 and all my games. I am officially retired from the gaming world.....\n\nUntil the PS5 comes out. 😂😂","Review_Sentiment":null,"Positive_Words":null,"Product_Price":null,"User_Age":null,"Negetive_Words":null,"User_ID":136500659,"User_Name":"YT:Breusley 🇭🇹","Product_Name":null}
