{"Review_Headline":null,"Review_Date":"Fri Sep 11 17:00:08 +0000 2020","Review_Rating":null,"Product_Category":null,"Review_Source":"Twitter","Source_Product_Review_ID":"twitter#piiaa⁷#439","User_Location":null,"Review_Text":"RT @LemonamuRM: #Namjooning 200912\n\nStarry Beach, 2020 by a'strict\n- Multi-channel projected installation with sound, dimensions variable\n-…","Review_Sentiment":null,"Positive_Words":null,"Product_Price":null,"User_Age":null,"Negetive_Words":null,"User_ID":1075983009138933800,"User_Name":"piiaa⁷","Product_Name":null}
