{"Review_Headline":null,"Review_Date":"Fri Sep 11 17:00:25 +0000 2020","Review_Rating":null,"Product_Category":null,"Review_Source":"Twitter","Source_Product_Review_ID":"twitter#justin#171","User_Location":"space","Review_Text":"@dark1x John have you seen this? Makes me worried for cross platform and Series X :( https://t.co/kDczoNsQWN","Review_Sentiment":null,"Positive_Words":null,"Product_Price":null,"User_Age":null,"Negetive_Words":null,"User_ID":1256683118997713000,"User_Name":"justin","Product_Name":null}
