{"Review_Headline":null,"Review_Date":"Fri Sep 11 17:00:32 +0000 2020","Review_Rating":null,"Product_Category":null,"Review_Source":"Twitter","Source_Product_Review_ID":"twitter#DigiTech Bytes#122","User_Location":"Dubai, United Arab Emirates","Review_Text":"Bose Introduces QuietComfort Earbuds and Sport Earbuds to take on Apple AirPods Pro\n\nhttps://t.co/l2PRYldPdQ… https://t.co/4epHOZ11FV","Review_Sentiment":null,"Positive_Words":null,"Product_Price":null,"User_Age":null,"Negetive_Words":null,"User_ID":1263643204232061000,"User_Name":"DigiTech Bytes","Product_Name":null}
