{"Review_Headline":null,"Review_Date":"Fri Sep 11 17:00:47 +0000 2020","Review_Rating":null,"Product_Category":null,"Review_Source":"Twitter","Source_Product_Review_ID":"twitter#MuchoGaming 🇲🇽 #NiCensuraNiCandados#464","User_Location":"México","Review_Text":"RT @RandyLoss: Another Pic #ps5 #preorder https://t.co/Ysmo9U52gH","Review_Sentiment":null,"Positive_Words":null,"Product_Price":null,"User_Age":null,"Negetive_Words":null,"User_ID":4446975612,"User_Name":"MuchoGaming 🇲🇽 #NiCensuraNiCandados","Product_Name":null}
