{"Review_Headline":null,"Review_Date":"Fri Sep 11 17:01:00 +0000 2020","Review_Rating":null,"Product_Category":null,"Review_Source":"Twitter","Source_Product_Review_ID":"twitter#Aldershot Town FC#146","User_Location":"The EBB Stadium, Aldershot","Review_Text":"🗣️THE WEEKLY UPDATE FROM YOUR CLUB: The latest of our weekly updates during the run-up to the new season (11th Sept… https://t.co/JLkFyUn2vM","Review_Sentiment":null,"Positive_Words":null,"Product_Price":null,"User_Age":null,"Negetive_Words":null,"User_ID":205637838,"User_Name":"Aldershot Town FC","Product_Name":null}
