{"Review_Headline":null,"Review_Date":"Fri Sep 11 17:01:11 +0000 2020","Review_Rating":null,"Product_Category":null,"Review_Source":"Twitter","Source_Product_Review_ID":"twitter#Yu-Gi-Oh! TCG#184","User_Location":null,"Review_Text":"Duelists, the newest Forbidden &amp; Limited Lists (Effective Sept 14, 2020) have been posted.\n\n➡️ https://t.co/3ixDFS1aDQ","Review_Sentiment":null,"Positive_Words":null,"Product_Price":null,"User_Age":null,"Negetive_Words":null,"User_ID":2898008473,"User_Name":"Yu-Gi-Oh! TCG","Product_Name":null}
