{"Review_Headline":null,"Review_Date":"Wed Sep 09 19:28:46 +0000 2020","Review_Rating":null,"Product_Category":null,"Review_Source":"Twitter","Source_Product_Review_ID":"twitter#Penthouse Records#87","User_Location":"Kingston, Jamaica","Review_Text":"Penthouse Archives Vol. 2‼️ Available to STREAM now on #AppleMusic #Spotify #AmazonMusic‼️ Featuring TWO previously… https://t.co/MS7OWYDd4q","Review_Sentiment":null,"Positive_Words":null,"Product_Price":null,"User_Age":null,"Negetive_Words":null,"User_ID":198729067,"User_Name":"Penthouse Records","Product_Name":null}
